swish_qr/__init__.py
swish_qr/clear_qr_data.py
swish_qr/cli.py
swish_qr/png.py
swish_qr/qrcodegen.py
swish_qr/svg.py
swish_qr/svg_templates.py
swish_qr/swish-logo.png
swish_qr/swish_qr.py
swish_qr-0.3.6.dist-info/LICENSE
swish_qr-0.3.6.dist-info/METADATA
swish_qr-0.3.6.dist-info/WHEEL
swish_qr-0.3.6.dist-info/entry_points.txt
swish_qr-0.3.6.dist-info/top_level.txt
swish_qr-0.3.6.dist-info/RECORD
