Metadata-Version: 2.1
Name: swish-qr
Version: 0.3.6
Summary: Swish QR Code Python Library
Author-email: Fredrik Haglund <fr3h4g@gmail.com>
License: LICENSE
Project-URL: Homepage, https://github.com/fr3h4g/swish-qr-python
Classifier: Development Status :: 5 - Production/Stable
Classifier: Intended Audience :: Developers
Classifier: Topic :: Software Development :: Libraries :: Python Modules
Classifier: License :: OSI Approved :: MIT License
Classifier: Programming Language :: Python
Classifier: Programming Language :: Python :: 3
Classifier: Programming Language :: Python :: 3.7
Classifier: Programming Language :: Python :: 3.8
Classifier: Programming Language :: Python :: 3.9
Classifier: Programming Language :: Python :: 3.10
Requires-Python: >=3.7
License-File: LICENSE
Requires-Dist: pillow
Requires-Dist: numpy
Requires-Dist: click
Provides-Extra: dev
Requires-Dist: black ; extra == 'dev'
Requires-Dist: flake8 ; extra == 'dev'
Requires-Dist: pytest ; extra == 'dev'
Requires-Dist: invoke ; extra == 'dev'
Requires-Dist: pytest-cov ; extra == 'dev'
